qs_vod_metadata/__init__.py
qs_vod_metadata/__main__.py
qs_vod_metadata/config_read.py
qs_vod_metadata/md5_calc.py
qs_vod_metadata/md_gen.py
qs_vod_metadata/media_info.py
qs_vod_metadata/metadata_template.xml
qs_vod_metadata/metadata_templateBackup.xml
qs_vod_metadata/qs_metadata_template.xml
qs_vod_metadata/utils.py
qs_vod_metadata/vod_config.ini
qs_vod_metadata/vod_configBack.ini
qs_vod_metadata/vodpackage.py
qs_vod_metadata/xml_helper.py
qs_vod_metadata-0.1.0.dist-info/DESCRIPTION.rst
qs_vod_metadata-0.1.0.dist-info/METADATA
qs_vod_metadata-0.1.0.dist-info/README.txt
qs_vod_metadata-0.1.0.dist-info/RECORD
qs_vod_metadata-0.1.0.dist-info/WHEEL
qs_vod_metadata-0.1.0.dist-info/metadata.json
qs_vod_metadata-0.1.0.dist-info/top_level.txt
tests/__init__.py
tests/test_vod_metadata.py
