Metadata-Version: 2.0
Name: qs-vod-metadata
Version: 0.1.0
Summary: CableLabs VOD Metadata 1.1 library and tools
Home-page: https://github.com/nkapowski/qs_vod_metadata
Author: Natalie Kapovski
Author-email: natalie@latto.tv
License: MIT
Keywords: cablelabs vod metadata
Platform: UNKNOWN
Classifier: Development Status :: 5 - Production/Stable
Classifier: Intended Audience :: Telecommunications Industry
Classifier: Topic :: Utilities
Classifier: License :: OSI Approved :: MIT License
Classifier: Programming Language :: Python :: 2.7
Classifier: Programming Language :: Python :: 3
